typist/__init__.py
typist/_core.py
typist/py.typed
bolton_typist-0.2.0.dist-info/METADATA
bolton_typist-0.2.0.dist-info/WHEEL
bolton_typist-0.2.0.dist-info/top_level.txt
bolton_typist-0.2.0.dist-info/RECORD
